README.md
setup.py
cookiedb_server.egg-info/PKG-INFO
cookiedb_server.egg-info/SOURCES.txt
cookiedb_server.egg-info/dependency_links.txt
cookiedb_server.egg-info/entry_points.txt
cookiedb_server.egg-info/requires.txt
cookiedb_server.egg-info/top_level.txt
cookiedbserver/__init__.py
cookiedbserver/__main__.py
cookiedbserver/auth.py
cookiedbserver/config.py
cookiedbserver/database.py
cookiedbserver/dmp.py
cookiedbserver/exceptions.py
cookiedbserver/server.py
test/test_server.py