Metadata-Version: 2.1
Name: cookiedb-server
Version: 1.0.2
Summary: Server for the CookieDB database
Home-page: https://github.com/jaedsonpys/cookiedb-server
Author: Jaedson Silva
Author-email: imunknowuser@protonmail.com
License: Apache 2.0
Keywords: server,database,cookiedb,socket
Platform: UNKNOWN
